LICENSE
MANIFEST.in
README.rst
setup.cfg
setup.py
artellapipe/__init__.py
artellapipe/libs/__init__.py
artellapipe/libs/naming/__init__.py
artellapipe/libs/naming/__logging__.ini
artellapipe/libs/naming/__version__.py
artellapipe/libs/naming/core/__init__.py
artellapipe/libs/naming/core/naminglib.py
artellapipe_libs_naming.egg-info/PKG-INFO
artellapipe_libs_naming.egg-info/SOURCES.txt
artellapipe_libs_naming.egg-info/dependency_links.txt
artellapipe_libs_naming.egg-info/not-zip-safe
artellapipe_libs_naming.egg-info/requires.txt
artellapipe_libs_naming.egg-info/top_level.txt
tests/__init__.py
tests/test_general.py