Metadata-Version: 2.1
Name: artellapipe-libs-naming
Version: 0.0.1
Summary: Library to manage nomenclature of project files, folders and DCC nodes
Home-page: https://github.com/ArtellaPipe/artellapipe-libs-naming
Author: Tomas Poveda
Author-email: tpovedatd@gmail.com
License: MIT
Platform: UNKNOWN
Provides-Extra: dev
Provides-Extra: test
